messenger_sdk
