Metadata-Version: 1.0
Name: messenger-sdk
Version: 0.1.13
Summary: Modern Factory Messenger Bot SDK
Home-page: https://github.com/modernfactory/messenger-sdk
Author: Marcin Szepczynski, Grzegorz Waszkowiak
Author-email: marcin@modernfactory.pl, grzegorz.waszkowiak@modernfactory.pl
License: MIT
Platform: UNKNOWN
